[{"iob":7.587,"activity":0.0661,"bolussnooze":0.008,"basaliob":0.268,"netbasalinsulin":0.85,"hightempinsulin":1.5,"time":"2016-05-22T10:39:10.000Z"},{"iob":7.185,"activity":0.0701,"bolussnooze":0,"basaliob":0.176,"netbasalinsulin":0.8,"hightempinsulin":1.5,"time":"2016-05-22T10:44:10.000Z"},{"iob":6.765,"activity":0.0739,"bolussnooze":0,"basaliob":0.085,"netbasalinsulin":0.75,"hightempinsulin":1.5,"time":"2016-05-22T10:49:10.000Z"},{"iob":6.326,"activity":0.0777,"bolussnooze":0,"basaliob":-0.004,"netbasalinsulin":0.7,"hightempinsulin":1.5,"time":"2016-05-22T10:54:10.000Z"},{"iob":5.92,"activity":0.0812,"bolussnooze":0,"basaliob":-0.04,"netbasalinsulin":0.65,"hightempinsulin":1.45,"time":"2016-05-22T10:59:10.000Z"},{"iob":5.513,"activity":0.082,"bolussnooze":0,"basaliob":-0.073,"netbasalinsulin":0.65,"hightempinsulin":1.45,"time":"2016-05-22T11:04:10.000Z"},{"iob":5.117,"activity":0.0815,"bolussnooze":0,"basaliob":-0.103,"netbasalinsulin":0.65,"hightempinsulin":1.45,"time":"2016-05-22T11:09:10.000Z"},{"iob":4.728,"activity":0.081,"bolussnooze":0,"basaliob":-0.129,"netbasalinsulin":0.65,"hightempinsulin":1.45,"time":"2016-05-22T11:14:10.000Z"},{"iob":4.345,"activity":0.0805,"bolussnooze":0,"basaliob":-0.153,"netbasalinsulin":0.65,"hightempinsulin":1.45,"time":"2016-05-22T11:19:10.000Z"},{"iob":3.973,"activity":0.0793,"bolussnooze":0,"basaliob":-0.173,"netbasalinsulin":0.65,"hightempinsulin":1.45,"time":"2016-05-22T11:24:10.000Z"},{"iob":3.62,"activity":0.0768,"bolussnooze":0,"basaliob":-0.189,"netbasalinsulin":0.6,"hightempinsulin":1.4,"time":"2016-05-22T11:29:10.000Z"},{"iob":3.285,"activity":0.0745,"bolussnooze":0,"basaliob":-0.203,"netbasalinsulin":0.6,"hightempinsulin":1.4,"time":"2016-05-22T11:34:10.000Z"},{"iob":2.967,"activity":0.0722,"bolussnooze":0,"basaliob":-0.213,"netbasalinsulin":0.6,"hightempinsulin":1.4,"time":"2016-05-22T11:39:10.000Z"},{"iob":2.666,"activity":0.0698,"bolussnooze":0,"basaliob":-0.221,"netbasalinsulin":0.55,"hightempinsulin":1.35,"time":"2016-05-22T11:44:10.000Z"},{"iob":2.383,"activity":0.0676,"bolussnooze":0,"basaliob":-0.226,"netbasalinsulin":0.55,"hightempinsulin":1.35,"time":"2016-05-22T11:49:10.000Z"},{"iob":2.115,"activity":0.0652,"bolussnooze":0,"basaliob":-0.229,"netbasalinsulin":0.5,"hightempinsulin":1.3,"time":"2016-05-22T11:54:10.000Z"},{"iob":1.864,"activity":0.0631,"bolussnooze":0,"basaliob":-0.23,"netbasalinsulin":0.5,"hightempinsulin":1.3,"time":"2016-05-22T11:59:10.000Z"},{"iob":1.63,"activity":0.061,"bolussnooze":0,"basaliob":-0.228,"netbasalinsulin":0.5,"hightempinsulin":1.3,"time":"2016-05-22T12:04:10.000Z"},{"iob":1.411,"activity":0.0589,"bolussnooze":0,"basaliob":-0.225,"netbasalinsulin":0.5,"hightempinsulin":1.3,"time":"2016-05-22T12:09:10.000Z"},{"iob":1.209,"activity":0.0568,"bolussnooze":0,"basaliob":-0.22,"netbasalinsulin":0.5,"hightempinsulin":1.3,"time":"2016-05-22T12:14:10.000Z"},{"iob":1.022,"activity":0.0548,"bolussnooze":0,"basaliob":-0.214,"netbasalinsulin":0.5,"hightempinsulin":1.3,"time":"2016-05-22T12:19:10.000Z"},{"iob":0.85,"activity":0.0529,"bolussnooze":0,"basaliob":-0.207,"netbasalinsulin":0.55,"hightempinsulin":1.3,"time":"2016-05-22T12:24:10.000Z"},{"iob":0.694,"activity":0.0511,"bolussnooze":0,"basaliob":-0.199,"netbasalinsulin":0.6,"hightempinsulin":1.3,"time":"2016-05-22T12:29:10.000Z"},{"iob":0.554,"activity":0.0493,"bolussnooze":0,"basaliob":-0.189,"netbasalinsulin":0.65,"hightempinsulin":1.3,"time":"2016-05-22T12:34:10.000Z"},{"iob":0.428,"activity":0.0474,"bolussnooze":0,"basaliob":-0.179,"netbasalinsulin":0.65,"hightempinsulin":1.3,"time":"2016-05-22T12:39:10.000Z"},{"iob":0.318,"activity":0.0453,"bolussnooze":0,"basaliob":-0.167,"netbasalinsulin":0.6,"hightempinsulin":1.25,"time":"2016-05-22T12:44:10.000Z"},{"iob":0.222,"activity":0.0432,"bolussnooze":0,"basaliob":-0.155,"netbasalinsulin":0.55,"hightempinsulin":1.2,"time":"2016-05-22T12:49:10.000Z"},{"iob":0.142,"activity":0.0408,"bolussnooze":0,"basaliob":-0.143,"netbasalinsulin":0.4,"hightempinsulin":1.05,"time":"2016-05-22T12:54:10.000Z"},{"iob":0.077,"activity":0.0384,"bolussnooze":0,"basaliob":-0.13,"netbasalinsulin":0.2,"hightempinsulin":0.85,"time":"2016-05-22T12:59:10.000Z"},{"iob":0.025,"activity":0.0361,"bolussnooze":0,"basaliob":-0.116,"netbasalinsulin":0.05,"hightempinsulin":0.7,"time":"2016-05-22T13:04:10.000Z"},{"iob":-0.012,"activity":0.0336,"bolussnooze":0,"basaliob":-0.103,"netbasalinsulin":-0.15,"hightempinsulin":0.5,"time":"2016-05-22T13:09:10.000Z"},{"iob":-0.035,"activity":0.0314,"bolussnooze":0,"basaliob":-0.09,"netbasalinsulin":-0.3,"hightempinsulin":0.35,"time":"2016-05-22T13:14:10.000Z"},{"iob":-0.044,"activity":0.0291,"bolussnooze":0,"basaliob":-0.078,"netbasalinsulin":-0.5,"hightempinsulin":0.15,"time":"2016-05-22T13:19:10.000Z"},{"iob":-0.047,"activity":0.0077,"bolussnooze":0,"basaliob":-0.066,"netbasalinsulin":-0.65,"hightempinsulin":0,"time":"2016-05-22T13:24:10.000Z"},{"iob":-0.048,"activity":0.0073,"bolussnooze":0,"basaliob":-0.056,"netbasalinsulin":-0.65,"hightempinsulin":0,"time":"2016-05-22T13:29:10.000Z"},{"iob":-0.045,"activity":0.0068,"bolussnooze":0,"basaliob":-0.047,"netbasalinsulin":-0.65,"hightempinsulin":0,"time":"2016-05-22T13:34:10.000Z"},{"iob":-0.039,"activity":0.0064,"bolussnooze":0,"basaliob":-0.038,"netbasalinsulin":-0.65,"hightempinsulin":0,"time":"2016-05-22T13:39:10.000Z"},{"iob":-0.031,"activity":-0.0029,"bolussnooze":0,"basaliob":-0.031,"netbasalinsulin":-0.65,"hightempinsulin":0,"time":"2016-05-22T13:44:10.000Z"},{"iob":-0.024,"activity":-0.0028,"bolussnooze":0,"basaliob":-0.024,"netbasalinsulin":-0.65,"hightempinsulin":0,"time":"2016-05-22T13:49:10.000Z"},{"iob":-0.019,"activity":-0.0027,"bolussnooze":0,"basaliob":-0.019,"netbasalinsulin":-0.65,"hightempinsulin":0,"time":"2016-05-22T13:54:10.000Z"},{"iob":-0.014,"activity":-0.0024,"bolussnooze":0,"basaliob":-0.014,"netbasalinsulin":-0.6,"hightempinsulin":0,"time":"2016-05-22T13:59:10.000Z"},{"iob":-0.01,"activity":-0.0022,"bolussnooze":0,"basaliob":-0.01,"netbasalinsulin":-0.55,"hightempinsulin":0,"time":"2016-05-22T14:04:10.000Z"},{"iob":-0.007,"activity":-0.0019,"bolussnooze":0,"basaliob":-0.007,"netbasalinsulin":-0.5,"hightempinsulin":0,"time":"2016-05-22T14:09:10.000Z"},{"iob":-0.005,"activity":-0.0017,"bolussnooze":0,"basaliob":-0.005,"netbasalinsulin":-0.45,"hightempinsulin":0,"time":"2016-05-22T14:14:10.000Z"},{"iob":-0.003,"activity":-0.0015,"bolussnooze":0,"basaliob":-0.003,"netbasalinsulin":-0.4,"hightempinsulin":0,"time":"2016-05-22T14:19:10.000Z"},{"iob":-0.002,"activity":-0.0012,"bolussnooze":0,"basaliob":-0.002,"netbasalinsulin":-0.35,"hightempinsulin":0,"time":"2016-05-22T14:24:10.000Z"},{"iob":-0.001,"activity":-0.0009,"bolussnooze":0,"basaliob":-0.001,"netbasalinsulin":-0.25,"hightempinsulin":0,"time":"2016-05-22T14:29:10.000Z"},{"iob":0,"activity":-0.0007,"bolussnooze":0,"basaliob":0,"netbasalinsulin":-0.2,"hightempinsulin":0,"time":"2016-05-22T14:34:10.000Z"}]
