{
  "bg": 204, 
  "temp": "absolute", 
  "snoozeBG": 173, 
  "timestamp": "2016-05-20T23:45:52.570390", 
  "missing": [
    "duration", 
    "rate"
  ], 
  "reason": "Eventual BG 132>=125, temp 1.7 >~ req 1.633U/hr", 
  "eventualBG": 132, 
  "error": "missing required input fields", 
  "input": {
    "reason": "Eventual BG 132>=125, temp 1.7 >~ req 1.633U/hr", 
    "bg": 204, 
    "eventualBG": 132, 
    "temp": "absolute", 
    "snoozeBG": 173, 
    "mealAssist": "Off: Carbs: undefined Boluses: undefined ISF: 45, Target: 116 Deviation: 18 BGI: -5.94", 
    "tick": "+0"
  }, 
  "mealAssist": "Off: Carbs: undefined Boluses: undefined ISF: 45, Target: 116 Deviation: 18 BGI: -5.94", 
  "tick": "+0"
}