{
  "bg": 106, 
  "temp": "absolute", 
  "snoozeBG": 108, 
  "timestamp": "2016-05-02T22:20:45.935903", 
  "missing": [
    "duration", 
    "rate"
  ], 
  "reason": "Eventual BG 108>106 but Avg. Delta 0.00 < Exp. Delta 2.9, temp 0.9 ~ req 0.9U/hr", 
  "eventualBG": 108, 
  "error": "missing required input fields", 
  "input": {
    "reason": "Eventual BG 108>106 but Avg. Delta 0.00 < Exp. Delta 2.9, temp 0.9 ~ req 0.9U/hr", 
    "bg": 106, 
    "eventualBG": 108, 
    "temp": "absolute", 
    "snoozeBG": 108, 
    "mealAssist": "Off: Carbs: undefined Boluses: undefined Target: 116 Deviation: -17 BGI: 2.79", 
    "tick": "+2"
  }, 
  "mealAssist": "Off: Carbs: undefined Boluses: undefined Target: 116 Deviation: -17 BGI: 2.79", 
  "tick": "+2"
}