{
  "bg": 209, 
  "temp": "absolute", 
  "snoozeBG": 119, 
  "timestamp": "2016-05-06T01:50:40.808612", 
  "missing": [
    "duration", 
    "rate"
  ], 
  "reason": "Eventual BG 34<106, bolus snooze: eventual BG range 34-119, temp 0.675 ~ req 0.7U/hr", 
  "eventualBG": 34, 
  "error": "missing required input fields", 
  "input": {
    "reason": "Eventual BG 34<106, bolus snooze: eventual BG range 34-119, temp 0.675 ~ req 0.7U/hr", 
    "bg": 209, 
    "eventualBG": 34, 
    "temp": "absolute", 
    "snoozeBG": 119, 
    "mealAssist": "Off: Carbs: undefined Boluses: undefined Target: 116 Deviation: 13 BGI: -11.52", 
    "tick": -2
  }, 
  "mealAssist": "Off: Carbs: undefined Boluses: undefined Target: 116 Deviation: 13 BGI: -11.52", 
  "tick": -2
}