{
  "bg": 69, 
  "temp": "absolute", 
  "snoozeBG": 102, 
  "timestamp": "2016-05-12T17:45:56.385591", 
  "missing": [
    "duration", 
    "rate"
  ], 
  "reason": "BG 69<78, but 21m left and 0 ~ req 0U/hr: no action required", 
  "eventualBG": 102, 
  "error": "missing required input fields", 
  "input": {
    "reason": "BG 69<78, but 21m left and 0 ~ req 0U/hr: no action required", 
    "bg": 69, 
    "eventualBG": 102, 
    "temp": "absolute", 
    "snoozeBG": 102, 
    "mealAssist": "Off: Carbs: undefined Boluses: undefined Target: 116 Deviation: -20 BGI: 2.34", 
    "tick": "+0"
  }, 
  "mealAssist": "Off: Carbs: undefined Boluses: undefined Target: 116 Deviation: -20 BGI: 2.34", 
  "tick": "+0"
}