[
  {
    "trend_arrow": "FLAT", 
    "display_time": "2016-05-25T08:41:55-07:00", 
    "system_time": "2016-05-25T14:39:05-07:00", 
    "direction": "Flat", 
    "sgv": 98, 
    "dateString": "2016-05-25T08:41:55-07:00", 
    "device": "openaps://cgm", 
    "unfiltered": 134752, 
    "rssi": 451, 
    "date": 1464190915000, 
    "filtered": 133920, 
    "type": "sgv", 
    "glucose": 98
  }, 
  {
    "trend_arrow": "FLAT", 
    "display_time": "2016-05-25T08:36:55-07:00", 
    "system_time": "2016-05-25T14:34:04-07:00", 
    "direction": "Flat", 
    "sgv": 98, 
    "dateString": "2016-05-25T08:36:55-07:00", 
    "device": "openaps://cgm", 
    "unfiltered": 134464, 
    "rssi": 176, 
    "date": 1464190615000, 
    "filtered": 133024, 
    "type": "sgv", 
    "glucose": 98
  }
]