[
  {
    "carbs": "0", 
    "bg": "206", 
    "ratio": "15", 
    "bolus": {
      "_type": "Bolus", 
      "_description": "Bolus 2016-07-05T12:11:29 head[4], body[0] op[0x01]", 
      "timestamp": "2016-07-05T12:11:29-07:00", 
      "_body": "", 
      "appended": [
        {
          "_type": "UnabsorbedInsulinBolus", 
          "_description": "UnabsorbedInsulinBolus unknown head[17], body[0] op[0x5c]", 
          "_body": "", 
          "_head": "5c11081b04587f0410ed043e6514266f14", 
          "data": [
            {
              "amount": 0.2, 
              "age": 27
            }, 
            {
              "amount": 2.2, 
              "age": 127
            }, 
            {
              "amount": 0.4, 
              "age": 237
            }, 
            {
              "amount": 1.55, 
              "age": 357
            }, 
            {
              "amount": 0.95, 
              "age": 367
            }
          ], 
          "_date": ""
        }
      ], 
      "programmed": 0.8, 
      "_head": "01080800", 
      "amount": 0.8, 
      "duration": 0, 
      "type": "normal", 
      "_date": "5dcb4c0510"
    }, 
    "timestamp": "2016-07-05T12:11:29-07:00", 
    "created_at": "2016-07-05T12:11:29-07:00", 
    "glucoseType": "BolusWizard", 
    "enteredBy": "openaps://medtronic/522", 
    "wizard": {
      "_type": "BolusWizard", 
      "bg": 206, 
      "bg_target_high": 125, 
      "correction_estimate": 0.2, 
      "unknown_byte[10]": 0, 
      "_description": "BolusWizard 2016-07-05T12:11:29 head[2], body[13] op[0x5b]", 
      "timestamp": "2016-07-05T12:11:29-07:00", 
      "_body": "00500f2d6a120000000c00067d", 
      "unknown_byte[8]": 0, 
      "bolus_estimate": 0.6, 
      "carb_ratio": 15, 
      "food_estimate": 0, 
      "unabsorbed_insulin_total": 1.2, 
      "_byte[5]": 18, 
      "carb_input": 0, 
      "_head": "5bce", 
      "unabsorbed_insulin_count": "??", 
      "_byte[7]": 0, 
      "sensitivity": 45, 
      "_date": "5dcb0c0510", 
      "bg_target_low": 106
    }, 
    "insulin": "0.8", 
    "eventType": "Correction Bolus", 
    "duration": "0", 
    "notes": "Normal bolus with wizard.\nProgrammed bolus 0.8\nDelivered bolus 0.8\nPercent delivered:  100%\nFood estimate 0\nCorrection estimate 0.2\nBolus estimate 0.6\nTarget low 106\nTarget high 125\nHypothetical glucose delta -36\nGlucose was: 206", 
    "medtronic": "mm://openaps/mm-format-ns-treatments/Correction Bolus", 
    "glucose": "206"
  }, 
  {
    "_type": "CalBGForPH", 
    "_description": "CalBGForPH 2016-07-05T12:11:25 head[2], body[0] op[0x0a]", 
    "timestamp": "2016-07-05T12:11:25-07:00", 
    "_body": "", 
    "glucoseType": "Finger", 
    "_head": "0ace", 
    "enteredBy": "openaps://medtronic/522", 
    "amount": 206, 
    "medtronic": "mm://openaps/mm-format-ns-treatments/CalBGForPH", 
    "eventType": "BG Check", 
    "created_at": "2016-07-05T12:11:25-07:00", 
    "_date": "59cb2c0510", 
    "glucose": 206
  }
]