[
  {
    "trend_arrow": "FLAT", 
    "display_time": "2016-05-07T15:23:00-07:00", 
    "system_time": "2016-05-07T21:20:09-07:00", 
    "direction": "Flat", 
    "sgv": 97, 
    "dateString": "2016-05-07T15:23:00-07:00", 
    "device": "openaps://cgm", 
    "unfiltered": 119872, 
    "rssi": 176, 
    "date": 1462659780000, 
    "filtered": 121376, 
    "type": "sgv", 
    "glucose": 97
  }, 
  {
    "trend_arrow": "FLAT", 
    "display_time": "2016-05-07T15:18:00-07:00", 
    "system_time": "2016-05-07T21:15:09-07:00", 
    "direction": "Flat", 
    "sgv": 98, 
    "dateString": "2016-05-07T15:18:00-07:00", 
    "device": "openaps://cgm", 
    "unfiltered": 120992, 
    "rssi": 168, 
    "date": 1462659480000, 
    "filtered": 121440, 
    "type": "sgv", 
    "glucose": 98
  }
]