[
  {
    "trend_arrow": "FLAT", 
    "display_time": "2016-07-10T03:31:11-07:00", 
    "noise": 1, 
    "system_time": "2016-07-10T09:26:19-07:00", 
    "direction": "Flat", 
    "sgv": 172, 
    "dateString": "2016-07-10T03:31:11-07:00", 
    "device": "openaps://cgm", 
    "unfiltered": 207872, 
    "rssi": 437, 
    "date": 1468146671000, 
    "filtered": 208672, 
    "type": "sgv", 
    "glucose": 172
  }, 
  {
    "trend_arrow": "FLAT", 
    "display_time": "2016-07-10T05:06:10-07:00", 
    "noise": 1, 
    "system_time": "2016-07-10T11:01:18-07:00", 
    "direction": "Flat", 
    "sgv": 172, 
    "dateString": "2016-07-10T05:06:10-07:00", 
    "device": "openaps://cgm", 
    "unfiltered": 208160, 
    "rssi": 181, 
    "date": 1468152370000, 
    "filtered": 208320, 
    "type": "sgv", 
    "glucose": 172
  }, 
  {
    "trend_arrow": "FLAT", 
    "display_time": "2016-07-10T05:01:10-07:00", 
    "noise": 1, 
    "system_time": "2016-07-10T10:56:18-07:00", 
    "direction": "Flat", 
    "sgv": 175, 
    "dateString": "2016-07-10T05:01:10-07:00", 
    "device": "openaps://cgm", 
    "unfiltered": 211232, 
    "rssi": 182, 
    "date": 1468152070000, 
    "filtered": 206720, 
    "type": "sgv", 
    "glucose": 175
  }
]