[
  {
    "trend_arrow": "FLAT", 
    "display_time": "2016-05-15T04:57:33-07:00", 
    "system_time": "2016-05-15T10:54:42-07:00", 
    "direction": "Flat", 
    "sgv": 212, 
    "dateString": "2016-05-15T04:57:33-07:00", 
    "device": "openaps://cgm", 
    "unfiltered": 252832, 
    "rssi": 458, 
    "date": 1463313453000, 
    "filtered": 253088, 
    "type": "sgv", 
    "glucose": 212
  }, 
  {
    "trend_arrow": "FLAT", 
    "display_time": "2016-05-15T04:52:32-07:00", 
    "system_time": "2016-05-15T10:49:42-07:00", 
    "direction": "Flat", 
    "sgv": 214, 
    "dateString": "2016-05-15T04:52:32-07:00", 
    "device": "openaps://cgm", 
    "unfiltered": 255008, 
    "rssi": 197, 
    "date": 1463313152000, 
    "filtered": 255328, 
    "type": "sgv", 
    "glucose": 214
  }, 
  {
    "trend_arrow": "FLAT", 
    "display_time": "2016-05-15T06:17:32-07:00", 
    "system_time": "2016-05-15T12:14:41-07:00", 
    "direction": "Flat", 
    "sgv": 228, 
    "dateString": "2016-05-15T06:17:32-07:00", 
    "device": "openaps://cgm", 
    "unfiltered": 268608, 
    "rssi": 201, 
    "date": 1463318252000, 
    "filtered": 266112, 
    "type": "sgv", 
    "glucose": 228
  }, 
  {
    "trend_arrow": "FLAT", 
    "display_time": "2016-05-15T06:12:32-07:00", 
    "system_time": "2016-05-15T12:09:41-07:00", 
    "direction": "Flat", 
    "sgv": 227, 
    "dateString": "2016-05-15T06:12:32-07:00", 
    "device": "openaps://cgm", 
    "unfiltered": 268160, 
    "rssi": 200, 
    "date": 1463317952000, 
    "filtered": 263552, 
    "type": "sgv", 
    "glucose": 227
  }
]