[
  {
    "trend_arrow": "DOUBLE_UP", 
    "display_time": "2016-06-06T07:16:12-07:00", 
    "system_time": "2016-06-06T13:13:21-07:00", 
    "direction": "DoubleUp", 
    "sgv": 110, 
    "dateString": "2016-06-06T07:16:12-07:00", 
    "device": "openaps://cgm", 
    "unfiltered": 137920, 
    "rssi": 189, 
    "date": 1465222572000, 
    "filtered": 115024, 
    "type": "sgv", 
    "glucose": 110
  }, 
  {
    "trend_arrow": "DOUBLE_UP", 
    "display_time": "2016-06-06T07:11:12-07:00", 
    "system_time": "2016-06-06T13:08:22-07:00", 
    "direction": "DoubleUp", 
    "sgv": 99, 
    "dateString": "2016-06-06T07:11:12-07:00", 
    "device": "openaps://cgm", 
    "unfiltered": 127136, 
    "rssi": 186, 
    "date": 1465222272000, 
    "filtered": 98960, 
    "type": "sgv", 
    "glucose": 99
  }
]