[
  {
    "trend_arrow": "NOT_COMPUTABLE", 
    "display_time": "2016-05-27T21:01:46-07:00", 
    "system_time": "2016-05-28T02:58:55-07:00", 
    "direction": "NOT COMPUTABLE", 
    "sgv": 137, 
    "dateString": "2016-05-27T21:01:46-07:00", 
    "device": "openaps://cgm", 
    "unfiltered": 188736, 
    "rssi": 185, 
    "date": 1464408106000, 
    "filtered": 176480, 
    "type": "sgv", 
    "glucose": 137
  }, 
  {
    "trend_arrow": "NOT_COMPUTABLE", 
    "display_time": "2016-05-27T20:56:46-07:00", 
    "system_time": "2016-05-28T02:53:55-07:00", 
    "direction": "NOT COMPUTABLE", 
    "sgv": 133, 
    "dateString": "2016-05-27T20:56:46-07:00", 
    "device": "openaps://cgm", 
    "unfiltered": 191744, 
    "rssi": 183, 
    "date": 1464407806000, 
    "filtered": 172320, 
    "type": "sgv", 
    "glucose": 133
  }
]