[
  {
    "trend_arrow": "FLAT", 
    "display_time": "2016-05-02T17:03:18-07:00", 
    "system_time": "2016-05-02T23:00:27-07:00", 
    "direction": "Flat", 
    "dateString": "2016-05-02T17:03:18-07:00", 
    "date": 1462233798000, 
    "unfiltered": 87872, 
    "filtered": 95232, 
    "device": "openaps://cgm", 
    "rssi": 178, 
    "sgv": 47, 
    "type": "sgv", 
    "glucose": 47
  }, 
  {
    "trend_arrow": "FLAT", 
    "display_time": "2016-05-02T16:58:18-07:00", 
    "system_time": "2016-05-02T22:55:28-07:00", 
    "direction": "Flat", 
    "dateString": "2016-05-02T16:58:18-07:00", 
    "date": 1462233498000, 
    "unfiltered": 93776, 
    "filtered": 98896, 
    "device": "openaps://cgm", 
    "rssi": 444, 
    "sgv": 54, 
    "type": "sgv", 
    "glucose": 54
  }, 
  {
    "trend_arrow": "FLAT", 
    "display_time": "2016-05-02T16:53:18-07:00", 
    "system_time": "2016-05-02T22:50:27-07:00", 
    "direction": "Flat", 
    "dateString": "2016-05-02T16:53:18-07:00", 
    "date": 1462233198000, 
    "unfiltered": 97520, 
    "filtered": 102176, 
    "device": "openaps://cgm", 
    "rssi": 185, 
    "sgv": 58, 
    "type": "sgv", 
    "glucose": 58
  }
]