[
  {
    "trend_arrow": "45_UP", 
    "display_time": "2016-05-08T20:07:55-07:00", 
    "direction": "FortyFiveUp", 
    "system_time": "2016-05-09T02:05:05-07:00", 
    "sgv": 90, 
    "dateString": "2016-05-08T20:07:55-07:00", 
    "device": "openaps://cgm", 
    "unfiltered": 113824, 
    "rssi": 184, 
    "date": 1462763275000.0, 
    "filtered": 103232, 
    "type": "sgv", 
    "glucose": 90
  }, 
  {
    "trend_arrow": "FLAT", 
    "display_time": "2016-05-08T20:02:55-07:00", 
    "direction": "Flat", 
    "system_time": "2016-05-09T02:00:05-07:00", 
    "sgv": 82, 
    "dateString": "2016-05-08T20:02:55-07:00", 
    "device": "openaps://cgm", 
    "unfiltered": 106448, 
    "rssi": 171, 
    "date": 1462762975000.0, 
    "filtered": 100416, 
    "type": "sgv", 
    "glucose": 82
  }, 
  {
    "trend_arrow": "FLAT", 
    "display_time": "2016-05-08T19:57:55-07:00", 
    "direction": "Flat", 
    "system_time": "2016-05-09T01:55:05-07:00", 
    "sgv": 76, 
    "dateString": "2016-05-08T19:57:55-07:00", 
    "device": "openaps://cgm", 
    "unfiltered": 101088, 
    "rssi": 180, 
    "date": 1462762675000.0, 
    "filtered": 100096, 
    "type": "sgv", 
    "glucose": 76
  }, 
  {
    "trend_arrow": "FLAT", 
    "display_time": "2016-05-08T19:52:56-07:00", 
    "direction": "Flat", 
    "system_time": "2016-05-09T01:50:05-07:00", 
    "sgv": 73, 
    "dateString": "2016-05-08T19:52:56-07:00", 
    "device": "openaps://cgm", 
    "unfiltered": 99296, 
    "rssi": 180, 
    "date": 1462762376000.0, 
    "filtered": 101104, 
    "type": "sgv", 
    "glucose": 73
  }, 
  {
    "trend_arrow": "FLAT", 
    "display_time": "2016-05-08T19:47:55-07:00", 
    "direction": "Flat", 
    "system_time": "2016-05-09T01:45:05-07:00", 
    "sgv": 74, 
    "dateString": "2016-05-08T19:47:55-07:00", 
    "device": "openaps://cgm", 
    "unfiltered": 99872, 
    "rssi": 179, 
    "date": 1462762075000.0, 
    "filtered": 102352, 
    "type": "sgv", 
    "glucose": 74
  }, 
  {
    "trend_arrow": "FLAT", 
    "display_time": "2016-05-08T19:42:55-07:00", 
    "direction": "Flat", 
    "system_time": "2016-05-09T01:40:05-07:00", 
    "sgv": 76, 
    "dateString": "2016-05-08T19:42:55-07:00", 
    "device": "openaps://cgm", 
    "unfiltered": 101648, 
    "rssi": 184, 
    "date": 1462761775000.0, 
    "filtered": 103424, 
    "type": "sgv", 
    "glucose": 76
  }, 
  {
    "trend_arrow": "FLAT", 
    "display_time": "2016-05-08T19:37:56-07:00", 
    "direction": "Flat", 
    "system_time": "2016-05-09T01:35:05-07:00", 
    "sgv": 78, 
    "dateString": "2016-05-08T19:37:56-07:00", 
    "device": "openaps://cgm", 
    "unfiltered": 103296, 
    "rssi": 168, 
    "date": 1462761476000.0, 
    "filtered": 104560, 
    "type": "sgv", 
    "glucose": 78
  }, 
  {
    "trend_arrow": "FLAT", 
    "display_time": "2016-05-08T19:32:55-07:00", 
    "direction": "Flat", 
    "system_time": "2016-05-09T01:30:05-07:00", 
    "sgv": 79, 
    "dateString": "2016-05-08T19:32:55-07:00", 
    "device": "openaps://cgm", 
    "unfiltered": 104288, 
    "rssi": 175, 
    "date": 1462761175000.0, 
    "filtered": 106064, 
    "type": "sgv", 
    "glucose": 79
  }, 
  {
    "trend_arrow": "FLAT", 
    "display_time": "2016-05-08T19:27:55-07:00", 
    "direction": "Flat", 
    "system_time": "2016-05-09T01:25:05-07:00", 
    "sgv": 80, 
    "dateString": "2016-05-08T19:27:55-07:00", 
    "device": "openaps://cgm", 
    "unfiltered": 105072, 
    "rssi": 187, 
    "date": 1462760875000.0, 
    "filtered": 107888, 
    "type": "sgv", 
    "glucose": 80
  }, 
  {
    "trend_arrow": "FLAT", 
    "display_time": "2016-05-08T19:22:55-07:00", 
    "direction": "Flat", 
    "system_time": "2016-05-09T01:20:05-07:00", 
    "sgv": 82, 
    "dateString": "2016-05-08T19:22:55-07:00", 
    "device": "openaps://cgm", 
    "unfiltered": 106592, 
    "rssi": 177, 
    "date": 1462760575000.0, 
    "filtered": 109360, 
    "type": "sgv", 
    "glucose": 82
  }, 
  {
    "trend_arrow": "NOT_COMPUTABLE", 
    "display_time": "2016-05-08T19:17:56-07:00", 
    "direction": "NOT COMPUTABLE", 
    "system_time": "2016-05-09T01:15:05-07:00", 
    "sgv": 83, 
    "dateString": "2016-05-08T19:17:56-07:00", 
    "device": "openaps://cgm", 
    "unfiltered": 107984, 
    "rssi": 188, 
    "date": 1462760276000.0, 
    "filtered": 109872, 
    "type": "sgv", 
    "glucose": 83
  }, 
  {
    "trend_arrow": "NOT_COMPUTABLE", 
    "display_time": "2016-05-08T19:12:56-07:00", 
    "direction": "NOT COMPUTABLE", 
    "system_time": "2016-05-09T01:10:05-07:00", 
    "sgv": 86, 
    "dateString": "2016-05-08T19:12:56-07:00", 
    "device": "openaps://cgm", 
    "unfiltered": 109904, 
    "rssi": 177, 
    "date": 1462759976000.0, 
    "filtered": 109408, 
    "type": "sgv", 
    "glucose": 86
  }, 
  {
    "trend_arrow": "NOT_COMPUTABLE", 
    "display_time": "2016-05-08T19:07:56-07:00", 
    "direction": "NOT COMPUTABLE", 
    "system_time": "2016-05-09T01:05:06-07:00", 
    "sgv": 86, 
    "dateString": "2016-05-08T19:07:56-07:00", 
    "device": "openaps://cgm", 
    "unfiltered": 110416, 
    "rssi": 424, 
    "date": 1462759676000.0, 
    "filtered": 108512, 
    "type": "sgv", 
    "glucose": 86
  }, 
  {
    "trend_arrow": "NOT_COMPUTABLE", 
    "display_time": "2016-05-08T19:02:55-07:00", 
    "direction": "NOT COMPUTABLE", 
    "system_time": "2016-05-09T01:00:05-07:00", 
    "sgv": 85, 
    "dateString": "2016-05-08T19:02:55-07:00", 
    "device": "openaps://cgm", 
    "unfiltered": 109056, 
    "rssi": 168, 
    "date": 1462759375000.0, 
    "filtered": 108016, 
    "type": "sgv", 
    "glucose": 85
  }, 
  {
    "trend_arrow": "FLAT", 
    "display_time": "2016-05-08T18:42:56-07:00", 
    "direction": "Flat", 
    "system_time": "2016-05-09T00:40:05-07:00", 
    "sgv": 86, 
    "dateString": "2016-05-08T18:42:56-07:00", 
    "device": "openaps://cgm", 
    "unfiltered": 110432, 
    "rssi": 199, 
    "date": 1462758176000.0, 
    "filtered": 113392, 
    "type": "sgv", 
    "glucose": 86
  }, 
  {
    "trend_arrow": "FLAT", 
    "display_time": "2016-05-08T18:37:56-07:00", 
    "direction": "Flat", 
    "system_time": "2016-05-09T00:35:05-07:00", 
    "sgv": 88, 
    "dateString": "2016-05-08T18:37:56-07:00", 
    "device": "openaps://cgm", 
    "unfiltered": 112400, 
    "rssi": 182, 
    "date": 1462757876000.0, 
    "filtered": 115424, 
    "type": "sgv", 
    "glucose": 88
  }, 
  {
    "trend_arrow": "FLAT", 
    "display_time": "2016-05-08T18:32:56-07:00", 
    "direction": "Flat", 
    "system_time": "2016-05-09T00:30:05-07:00", 
    "sgv": 91, 
    "dateString": "2016-05-08T18:32:56-07:00", 
    "device": "openaps://cgm", 
    "unfiltered": 114512, 
    "rssi": 189, 
    "date": 1462757576000.0, 
    "filtered": 117488, 
    "type": "sgv", 
    "glucose": 91
  }, 
  {
    "trend_arrow": "FLAT", 
    "display_time": "2016-05-08T18:27:56-07:00", 
    "direction": "Flat", 
    "system_time": "2016-05-09T00:25:05-07:00", 
    "sgv": 93, 
    "dateString": "2016-05-08T18:27:56-07:00", 
    "device": "openaps://cgm", 
    "unfiltered": 116256, 
    "rssi": 208, 
    "date": 1462757276000.0, 
    "filtered": 119296, 
    "type": "sgv", 
    "glucose": 93
  }, 
  {
    "trend_arrow": "FLAT", 
    "display_time": "2016-05-08T18:22:56-07:00", 
    "direction": "Flat", 
    "system_time": "2016-05-09T00:20:05-07:00", 
    "sgv": 94, 
    "dateString": "2016-05-08T18:22:56-07:00", 
    "device": "openaps://cgm", 
    "unfiltered": 118000, 
    "rssi": 191, 
    "date": 1462756976000.0, 
    "filtered": 120464, 
    "type": "sgv", 
    "glucose": 94
  }, 
  {
    "trend_arrow": "FLAT", 
    "display_time": "2016-05-08T18:17:56-07:00", 
    "direction": "Flat", 
    "system_time": "2016-05-09T00:15:05-07:00", 
    "sgv": 96, 
    "dateString": "2016-05-08T18:17:56-07:00", 
    "device": "openaps://cgm", 
    "unfiltered": 119744, 
    "rssi": 190, 
    "date": 1462756676000.0, 
    "filtered": 120992, 
    "type": "sgv", 
    "glucose": 96
  }, 
  {
    "trend_arrow": "FLAT", 
    "display_time": "2016-05-08T18:12:56-07:00", 
    "direction": "Flat", 
    "system_time": "2016-05-09T00:10:05-07:00", 
    "sgv": 98, 
    "dateString": "2016-05-08T18:12:56-07:00", 
    "device": "openaps://cgm", 
    "unfiltered": 121632, 
    "rssi": 201, 
    "date": 1462756376000.0, 
    "filtered": 121264, 
    "type": "sgv", 
    "glucose": 98
  }
]