[
  {
    "_id": "56326be91c1181016e007622",
    "device": "dexcom",
    "date": 1446144999000,
    "dateString": "2015-10-29T18:56:39+00:00",
    "sgv": 76,
    "direction": "Flat",
    "noise": 1,
    "type": "sgv",
    "filtered": 91008,
    "unfiltered": 89264,
    "rssi": 203,
    "glucose": 76
  },
  {
    "_id": "56326abe1c1181016e007620",
    "device": "dexcom",
    "date": 1446144699000,
    "dateString": "2015-10-29T18:51:39+00:00",
    "sgv": 72,
    "direction": "Flat",
    "noise": 1,
    "type": "sgv",
    "filtered": 94688,
    "unfiltered": 85504,
    "rssi": 167,
    "glucose": 72
  },
  {
    "_id": "563269951c1181016e00761e",
    "device": "dexcom",
    "date": 1446144399000,
    "dateString": "2015-10-29T18:46:39+00:00",
    "sgv": 84,
    "direction": "Flat",
    "noise": 2,
    "type": "sgv",
    "filtered": 97488,
    "unfiltered": 92464,
    "rssi": 170,
    "glucose": 84
  },
  {
    "_id": "563268661c1181016e00761b",
    "device": "dexcom",
    "date": 1446144099000,
    "dateString": "2015-10-29T18:41:39+00:00",
    "sgv": 85,
    "direction": "Flat",
    "noise": 2,
    "type": "sgv",
    "filtered": 98160,
    "unfiltered": 97584,
    "rssi": 195,
    "glucose": 85
  },
  {
    "_id": "563267391c1181016e007619",
    "device": "dexcom",
    "date": 1446143799000,
    "dateString": "2015-10-29T18:36:39+00:00",
    "sgv": 83,
    "direction": "Flat",
    "noise": 2,
    "type": "sgv",
    "filtered": 96368,
    "unfiltered": 96848,
    "rssi": 186,
    "glucose": 83
  },
  {
    "_id": "5632660d1c1181016e007617",
    "device": "dexcom",
    "date": 1446143499000,
    "dateString": "2015-10-29T18:31:39+00:00",
    "sgv": 79,
    "direction": "Flat",
    "noise": 2,
    "type": "sgv",
    "filtered": 92752,
    "unfiltered": 96096,
    "rssi": 191,
    "glucose": 79
  },
  {
    "_id": "563264e11c1181016e007615",
    "device": "dexcom",
    "date": 1446143199000,
    "dateString": "2015-10-29T18:26:39+00:00",
    "sgv": 77,
    "direction": "Flat",
    "noise": 2,
    "type": "sgv",
    "filtered": 90000,
    "unfiltered": 97536,
    "rssi": 188,
    "glucose": 77
  },
  {
    "_id": "56326c7b1c1181016e007625",
    "device": "dexcom",
    "date": 1446142899000,
    "dateString": "2015-10-29T18:21:39+00:00",
    "sgv": 77,
    "direction": "Flat",
    "noise": 2,
    "type": "sgv",
    "filtered": 90464,
    "unfiltered": 95584,
    "rssi": 184,
    "glucose": 77
  },
  {
    "_id": "563263b51c1181016e007613",
    "device": "dexcom",
    "date": 1446142898000,
    "dateString": "2015-10-29T18:21:38+00:00",
    "sgv": 77,
    "direction": "Flat",
    "noise": 2,
    "type": "sgv",
    "filtered": 90464,
    "unfiltered": 95584,
    "rssi": 184,
    "glucose": 77
  },
  {
    "_id": "56326c7b1c1181016e007626",
    "device": "dexcom",
    "date": 1446142599000,
    "dateString": "2015-10-29T18:16:39+00:00",
    "sgv": 73,
    "direction": "Flat",
    "noise": 1,
    "type": "sgv",
    "filtered": 93760,
    "unfiltered": 86592,
    "rssi": 173,
    "glucose": 73
  }
]
