[
  {
    "_id": "560fa4448b87d75695262eca",
    "device": "dexcom",
    "date": 1443865662000,
    "dateString": "2015-10-03T09:47:42+00:00",
    "sgv": 75,
    "direction": "Flat",
    "noise": 1,
    "type": "sgv",
    "filtered": 61368,
    "unfiltered": 62216,
    "rssi": 193,
    "glucose": 75
  },
  {
    "_id": "560fa3188b87d75695262ec8",
    "device": "dexcom",
    "date": 1443865362000,
    "dateString": "2015-10-03T09:42:42+00:00",
    "sgv": 72,
    "direction": "Flat",
    "noise": 1,
    "type": "sgv",
    "filtered": 60904,
    "unfiltered": 60992,
    "rssi": 193,
    "glucose": 72
  },
  {
    "_id": "560fa1ed8b87d75695262ec6",
    "device": "dexcom",
    "date": 1443865062000,
    "dateString": "2015-10-03T09:37:42+00:00",
    "sgv": 73,
    "direction": "Flat",
    "noise": 1,
    "type": "sgv",
    "filtered": 60136,
    "unfiltered": 61344,
    "rssi": 194,
    "glucose": 73
  },
  {
    "_id": "560fa0bf8b87d75695262ec4",
    "device": "dexcom",
    "date": 1443864762000,
    "dateString": "2015-10-03T09:32:42+00:00",
    "sgv": 71,
    "direction": "Flat",
    "noise": 1,
    "type": "sgv",
    "filtered": 59248,
    "unfiltered": 60368,
    "rssi": 193,
    "glucose": 71
  },
  {
    "_id": "560f9f958b87d75695262ec2",
    "device": "dexcom",
    "date": 1443864462000,
    "dateString": "2015-10-03T09:27:42+00:00",
    "sgv": 71,
    "direction": "Flat",
    "noise": 1,
    "type": "sgv",
    "filtered": 58904,
    "unfiltered": 60232,
    "rssi": 193,
    "glucose": 71
  },
  {
    "_id": "560f9e698b87d75695262ec0",
    "device": "dexcom",
    "date": 1443864162000,
    "dateString": "2015-10-03T09:22:42+00:00",
    "sgv": 69,
    "direction": "Flat",
    "noise": 1,
    "type": "sgv",
    "filtered": 59704,
    "unfiltered": 59632,
    "rssi": 193,
    "glucose": 69
  },
  {
    "_id": "560f9d3d8b87d75695262ebe",
    "device": "dexcom",
    "date": 1443863862000,
    "dateString": "2015-10-03T09:17:42+00:00",
    "sgv": 74,
    "direction": "Flat",
    "noise": 2,
    "type": "sgv",
    "filtered": 61648,
    "unfiltered": 59104,
    "rssi": 194,
    "glucose": 74
  },
  {
    "_id": "560f9c0f8b87d75695262ebc",
    "device": "dexcom",
    "date": 1443863563000,
    "dateString": "2015-10-03T09:12:43+00:00",
    "sgv": 78,
    "direction": "Flat",
    "noise": 2,
    "type": "sgv",
    "filtered": 63816,
    "unfiltered": 59864,
    "rssi": 185,
    "glucose": 78
  },
  {
    "_id": "560f9ae58b87d75695262eba",
    "device": "dexcom",
    "date": 1443863262000,
    "dateString": "2015-10-03T09:07:42+00:00",
    "sgv": 81,
    "direction": "Flat",
    "noise": 2,
    "type": "sgv",
    "filtered": 64840,
    "unfiltered": 62008,
    "rssi": 190,
    "glucose": 81
  },
  {
    "_id": "560f99b88b87d75695262eb8",
    "device": "dexcom",
    "date": 1443862962000,
    "dateString": "2015-10-03T09:02:42+00:00",
    "sgv": 79,
    "direction": "Flat",
    "noise": 2,
    "type": "sgv",
    "filtered": 64216,
    "unfiltered": 63496,
    "rssi": 189,
    "glucose": 79
  }
]
